test_mrb/__init__.py
test_mrb/configure/__init__.py
test_mrb/configure/alias.py
test_mrb/configure/main.py
test_mrb/configure/scripts.py
test_mrb-0.0.0.dist-info/LICENSE
test_mrb-0.0.0.dist-info/METADATA
test_mrb-0.0.0.dist-info/WHEEL
test_mrb-0.0.0.dist-info/entry_points.txt
test_mrb-0.0.0.dist-info/top_level.txt
test_mrb-0.0.0.dist-info/RECORD
